<?xml version="1.0" encoding="utf-8"?>
<!DOCTYPE hibernate-mapping PUBLIC "-//Hibernate/Hibernate Mapping DTD 3.0//EN"
"http://hibernate.sourceforge.net/hibernate-mapping-3.0.dtd">
<!-- 
    Mapping file autogenerated by MyEclipse Persistence Tools
-->
<hibernate-mapping>
    <class name="com.pwa.data.model.head.Head" table="head" >
         <id name="id" type="java.lang.String">
            <column name="ID" length="7" />
        </id>
        <property name="br" type="java.lang.String">
            <column name="BR" length="7" />
        </property>
        <property name="rte" type="java.lang.String">
            <column name="RTE" length="6" />
        </property>
        <property name="totnew" type="java.lang.String">
            <column name="TOTNEW" length="6" />
        </property>
        <property name="totrec" type="java.lang.String">
            <column name="TOTREC" length="6" />
        </property>
        <property name="totread" type="java.lang.String">
            <column name="TOTREAD" length="6" />
        </property>
        <property name="readerid" type="java.lang.String">
            <column name="READERID" length="4" />
        </property>
        <property name="assigndate" type="java.lang.String">
            <column name="ASSIGNDATE" length="2" />
        </property>
        <property name="sendflag" type="java.lang.String">
            <column name="SENDFLAG" length="1" />
        </property>
    </class>
</hibernate-mapping>
